pymhub/__init__.py
pymhub/testrequests.py
pymhub-0.6.dist-info/LICENSE
pymhub-0.6.dist-info/METADATA
pymhub-0.6.dist-info/WHEEL
pymhub-0.6.dist-info/top_level.txt
pymhub-0.6.dist-info/zip-safe
pymhub-0.6.dist-info/RECORD
