Metadata-Version: 2.1
Name: pymhub
Version: 0.6
Summary: Python API for talking to HDAnywhere HDBaseT Matrix
Home-page: https://github.com/tvrulesme/pymhub
Author: John Williamson
Author-email: john.williamson.1975@gmail.com
License: MIT
Download-URL: https://github.com/tvrulesme/pymhub/archive/0.6.tar.gz
Platform: UNKNOWN
Classifier: Development Status :: 4 - Beta
Classifier: Programming Language :: Python :: 3.5
